LICENSE
README.md
setup.py
python3_pytun.egg-info/PKG-INFO
python3_pytun.egg-info/SOURCES.txt
python3_pytun.egg-info/dependency_links.txt
python3_pytun.egg-info/top_level.txt
pytun/__init__.py